AXUI
