Metadata-Version: 1.1
Name: AXUI
Version: 0.2.3
Summary: A cross platform UI auto framework
Home-page: https://github.com/xcgspring/AXUI
Author: xcgspring
Author-email: xcgspring@163.com
License: Apache Licence Version 2.0
Keywords: UI,automation
Platform: UNKNOWN
Classifier: Programming Language :: Python
Classifier: Programming Language :: Python :: 2
Classifier: Development Status :: 2 - Pre-Alpha
Classifier: Environment :: Console
Classifier: Intended Audience :: Developers
Classifier: License :: OSI Approved :: Apache Software License
Classifier: Operating System :: OS Independent
Classifier: Topic :: Software Development :: Libraries :: Python Modules
Classifier: Topic :: Software Development :: Quality Assurance
Classifier: Topic :: Software Development :: Testing
